pytest_flyte/__init__.py
pytest_flyte/plugin.py
pytest_flyte/docker/Dockerfile
pytest_flyte/docker/flyte-entrypoint-override.sh
pytest_flyte/templates/docker-compose.yaml.tmpl
pytest_flyte/templates/kustomization.yaml.tmpl
pytest_flyte-0.0.1.dist-info/METADATA
pytest_flyte-0.0.1.dist-info/WHEEL
pytest_flyte-0.0.1.dist-info/entry_points.txt
pytest_flyte-0.0.1.dist-info/top_level.txt
pytest_flyte-0.0.1.dist-info/RECORD
